{
  "bioguide_id": "H001090",
  "name": "Josh Harder",
  "party": "D",
  "chamber": "house",
  "state": "CA",
  "district": "9",
  "gender": "M",
  "photo_url": "https://unitedstates.github.io/images/congress/450x550/H001090.jpg",
  "serving_since": 2019,
  "years_in_office": 7,
  "funding": {
    "cycle": "2024",
    "total_raised": 3498156,
    "campaign_raised": 3498156,
    "leadership_pac_raised": 0,
    "top_industries": [
      {
        "code": "IND",
        "name": "Individual Contributions",
        "amount": 1760432,
        "donors": [
          {
            "name": "GOOGLE",
            "type": "Organization",
            "amount": 34120
          },
          {
            "name": "BESSEMER VENTURE PARTNERS",
            "type": "Organization",
            "amount": 29800
          },
          {
            "name": "STANFORD UNIVERSITY",
            "type": "Organization",
            "amount": 25550
          },
          {
            "name": "BOSTON CONSULTING GROUP",
            "type": "Organization",
            "amount": 19800
          },
          {
            "name": "COOLEY LLP",
            "type": "Organization",
            "amount": 16200
          },
          {
            "name": "OVO FUND",
            "type": "Organization",
            "amount": 14900
          },
          {
            "name": "LINDSAY GOLDBERG",
            "type": "Organization",
            "amount": 13200
          },
          {
            "name": "KEKER VAN NEST & PETERS LLP",
            "type": "Organization",
            "amount": 12900
          },
          {
            "name": "N Y F PROPERTIES INC.",
            "type": "Organization",
            "amount": 12400
          },
          {
            "name": "UC BERKELEY",
            "type": "Organization",
            "amount": 10909
          },
          {
            "name": "KEKER VAN NEST & PETERS",
            "type": "Organization",
            "amount": 10400
          },
          {
            "name": "UNIVERSITY OF CALIFORNIA BERKELEY",
            "type": "Organization",
            "amount": 10100
          },
          {
            "name": "PSAI REALTY PARTNERS",
            "type": "Organization",
            "amount": 9900
          },
          {
            "name": "MANAGING PARTNER",
            "type": "Organization",
            "amount": 9900
          },
          {
            "name": "BOOZ ALLEN HAMILTON",
            "type": "Organization",
            "amount": 9900
          },
          {
            "name": "COLLINEAR NETWORKS",
            "type": "Organization",
            "amount": 8800
          },
          {
            "name": "MYSELF - BB EVENTS",
            "type": "Organization",
            "amount": 8700
          },
          {
            "name": "CANTILLON CAPITAL",
            "type": "Organization",
            "amount": 8300
          },
          {
            "name": "AC WELLNESS",
            "type": "Organization",
            "amount": 8100
          },
          {
            "name": "CTS INC.",
            "type": "Organization",
            "amount": 8000
          },
          {
            "name": "APPLE INC.",
            "type": "Organization",
            "amount": 7825
          },
          {
            "name": "Y COMBINATOR",
            "type": "Organization",
            "amount": 7600
          },
          {
            "name": "APOLLO MANAGEMENT",
            "type": "Organization",
            "amount": 7600
          },
          {
            "name": "UC DAVIS",
            "type": "Organization",
            "amount": 7350
          },
          {
            "name": "THOMSON REUTERS",
            "type": "Organization",
            "amount": 7100
          },
          {
            "name": "LINKEDIN",
            "type": "Organization",
            "amount": 7100
          },
          {
            "name": "MORGAN STANLEY",
            "type": "Organization",
            "amount": 6866
          },
          {
            "name": "E + J GALLO WINERY",
            "type": "Organization",
            "amount": 6800
          },
          {
            "name": "RICHARD BEARD ARCHITECTS",
            "type": "Organization",
            "amount": 6800
          },
          {
            "name": "REED INTERNATIONAL",
            "type": "Organization",
            "amount": 6700
          },
          {
            "name": "DATAVANT",
            "type": "Organization",
            "amount": 6700
          },
          {
            "name": "BERGGRUEN GALLERY",
            "type": "Organization",
            "amount": 6700
          },
          {
            "name": "SMUDGE WELLNESS INC.",
            "type": "Organization",
            "amount": 6700
          },
          {
            "name": "NORTHWESTERN UNIVERSITY",
            "type": "Organization",
            "amount": 6600
          },
          {
            "name": "SPECTRUM EQUITY",
            "type": "Organization",
            "amount": 6600
          },
          {
            "name": "VABA",
            "type": "Organization",
            "amount": 6600
          },
          {
            "name": "HARVARD UNIVERSITY",
            "type": "Organization",
            "amount": 6600
          },
          {
            "name": "ABVIO INC.",
            "type": "Organization",
            "amount": 6600
          },
          {
            "name": "UNITED STAFFING ASSOCIATES",
            "type": "Organization",
            "amount": 6600
          },
          {
            "name": "HILLSPIRE LLC",
            "type": "Organization",
            "amount": 6600
          },
          {
            "name": "THE SCOTT FOUNDATION",
            "type": "Organization",
            "amount": 6600
          },
          {
            "name": "VENBIO PARTNERS LLC",
            "type": "Organization",
            "amount": 6600
          },
          {
            "name": "VALLEY STRONG CREDIT UNION",
            "type": "Organization",
            "amount": 6600
          },
          {
            "name": "EVERGREEN MONEY",
            "type": "Organization",
            "amount": 6600
          },
          {
            "name": "MORRISON & FOERSTER LLC",
            "type": "Organization",
            "amount": 6600
          },
          {
            "name": "META PLATFORMS",
            "type": "Organization",
            "amount": 6600
          },
          {
            "name": "EXECUTIVE AFFILIATES",
            "type": "Organization",
            "amount": 6600
          },
          {
            "name": "ADOBE INC",
            "type": "Organization",
            "amount": 6600
          },
          {
            "name": "LA CLINICA",
            "type": "Organization",
            "amount": 6600
          },
          {
            "name": "SHER EDLING LLP",
            "type": "Organization",
            "amount": 6600
          }
        ]
      },
      {
        "code": "PAC",
        "name": "PAC & Committee Contributions",
        "amount": 1737724,
        "donors": [
          {
            "name": "NRCC",
            "type": "PAC",
            "amount": 928232
          },
          {
            "name": "NATIONAL ASSOCIATION OF REALTORS POLITICAL ACTION COMMITTEE",
            "type": "PAC",
            "amount": 91397
          },
          {
            "name": "NATIONAL ASSOCIATION OF REALTORS",
            "type": "PAC",
            "amount": 73179
          },
          {
            "name": "MAJORITY PAC",
            "type": "PAC",
            "amount": 31100
          },
          {
            "name": "FRONTLINE USA",
            "type": "PAC",
            "amount": 11600
          },
          {
            "name": "JSTREETPAC",
            "type": "PAC",
            "amount": 10446
          },
          {
            "name": "INTERNATIONAL ASSOCIATION OF SHEET METAL, AIR, RAIL AND TRANSPORTATION WORKERS POLITICAL ACTION LEAGUE",
            "type": "PAC",
            "amount": 10000
          },
          {
            "name": "END CITIZENS UNITED",
            "type": "PAC",
            "amount": 10000
          },
          {
            "name": "INTERNATIONAL BROTHERHOOD OF ELECTRICAL WORKERS POLITICAL ACTION COMMITTEE",
            "type": "PAC",
            "amount": 10000
          },
          {
            "name": "AMERICAN FEDERATION OF STATE COUNTY & MUNICIPAL EMPLOYEES  P E O P L E",
            "type": "PAC",
            "amount": 10000
          },
          {
            "name": "NATIONAL AIR TRAFFIC CONTROLLERS ASSOCIATION PAC",
            "type": "PAC",
            "amount": 10000
          },
          {
            "name": "AMERICAN CRYSTAL SUGAR COMPANY POLITICAL ACTION COMMITTEE",
            "type": "PAC",
            "amount": 10000
          },
          {
            "name": "TRUTH TO POWER",
            "type": "PAC",
            "amount": 10000
          },
          {
            "name": "MACHINISTS NON PARTISAN POLITICAL LEAGUE OF THE INTERNATIONAL ASSOCIATION OF MACHINISTS & AEROSPACE WORKERS",
            "type": "PAC",
            "amount": 10000
          },
          {
            "name": "NEW DEMOCRAT COALITION ACTION FUND",
            "type": "PAC",
            "amount": 10000
          },
          {
            "name": "JOBS, EDUCATION, & FAMILIES FIRST  JEFF PAC",
            "type": "PAC",
            "amount": 10000
          },
          {
            "name": "AMERICAN FEDERATION OF TEACHERS, AFL-CIO COMMITTEE ON POLITICAL EDUCATION",
            "type": "PAC",
            "amount": 10000
          },
          {
            "name": "AMERIPAC: THE FUND FOR A GREATER AMERICA",
            "type": "PAC",
            "amount": 10000
          },
          {
            "name": "CARPENTERS LEGISLATIVE IMPROVEMENT COMMITTEE UNITED BROTHERHOOD OF CARPENTERS AND JOINERS",
            "type": "PAC",
            "amount": 10000
          },
          {
            "name": "SEIU COPE (SERVICE EMPLOYEES INTERNATIONAL UNION COMMITTEE ON POLITICAL EDUCATION)",
            "type": "PAC",
            "amount": 10000
          },
          {
            "name": "AIR LINE PILOTS ASSOCIATION PAC",
            "type": "PAC",
            "amount": 10000
          },
          {
            "name": "DAIRY FARMERS OF AMERICA, INC. POLITICAL ACTION COMMITTEE; AKA DFA-PAC",
            "type": "PAC",
            "amount": 8000
          },
          {
            "name": "INTERNATIONAL ASSOCIATION OF FIREFIGHTERS INTERESTED IN REGISTRATION AND EDUCATION PAC",
            "type": "PAC",
            "amount": 7500
          },
          {
            "name": "ACROSS THE AISLE PAC",
            "type": "PAC",
            "amount": 7500
          },
          {
            "name": "WINE AND SPIRITS WHOLESALERS OF AMERICA, INC. POLITICAL ACTION COMMITTEE",
            "type": "PAC",
            "amount": 7500
          },
          {
            "name": "D.R.I.V.E. - DEMOCRAT, REPUBLICAN, INDEPENDENT VOTER EDUCATION (THE PAC OF THE INTERNATIONAL BROTHERHOOD OF TEAMSTERS)",
            "type": "PAC",
            "amount": 7500
          },
          {
            "name": "AMERICAN ASSOCIATION FOR JUSTICE POLITICAL ACTION COMMITTEE (AAJ PAC)",
            "type": "PAC",
            "amount": 7500
          },
          {
            "name": "BLUE DIAMOND GROWERS POLITICAL ACTION COMMITTEE",
            "type": "PAC",
            "amount": 7500
          },
          {
            "name": "FAIR SHOT PAC",
            "type": "PAC",
            "amount": 7500
          },
          {
            "name": "WINE INSTITUTE PAC",
            "type": "PAC",
            "amount": 7500
          },
          {
            "name": "NATIONAL ASSOCIATION OF LETTER CARRIERS OF U.S.A. POLITICAL FUND (LETTER CARRIER POLITICAL FUND)",
            "type": "PAC",
            "amount": 7500
          },
          {
            "name": "NEA FUND FOR CHILDREN AND PUBLIC EDUCATION",
            "type": "PAC",
            "amount": 7000
          },
          {
            "name": "PUTTING NEW HAMPSHIRE FIRST",
            "type": "PAC",
            "amount": 6600
          },
          {
            "name": "CA LUV PAC (CALIFORNIA LEADERSHIP UNITED FOR VICTORY PAC)",
            "type": "PAC",
            "amount": 6500
          },
          {
            "name": "AMERICAN ISRAEL PUBLIC AFFAIRS COMMITTEE POLITICAL ACTION COMMITTEE",
            "type": "PAC",
            "amount": 6001
          },
          {
            "name": "ENGINEERS POLITICAL EDUCATION COMMITTEE (EPEC)/INTERNATIONAL UNION OF OPERATING ENGINEERS",
            "type": "PAC",
            "amount": 6000
          },
          {
            "name": "FOLEY & LARDNER POLITICAL FUND, INC.",
            "type": "PAC",
            "amount": 6000
          },
          {
            "name": "AMERICAN MEDICAL ASSOCIATION POLITICAL ACTION COMMITTEE",
            "type": "PAC",
            "amount": 6000
          },
          {
            "name": "UA UNION PLUMBERS & PIPEFITTERS VOTE! PAC (UNITED ASSOCIATION OF JOURNEYMEN AND APPRENTICES OF THE PLUMBING & PIPEFITTING INDUSTRY OF THE UNITED STATES AND CANADA)",
            "type": "PAC",
            "amount": 5000
          },
          {
            "name": "AMERICAN VETERINARY MEDICAL ASSOCIATION POLITICAL ACTION COMMITTEE",
            "type": "PAC",
            "amount": 5000
          },
          {
            "name": "PAC TO THE FUTURE",
            "type": "PAC",
            "amount": 5000
          },
          {
            "name": "PLANNED PARENTHOOD ACTION FUND INC PAC, DBA PLANNED PARENTHOOD FEDERAL PAC",
            "type": "PAC",
            "amount": 5000
          },
          {
            "name": "DEFEND THE DREAM",
            "type": "PAC",
            "amount": 5000
          },
          {
            "name": "ASIAN AMERICAN HOTEL OWNERS ASSOCIATION PAC (AAHOA PAC)",
            "type": "PAC",
            "amount": 5000
          },
          {
            "name": "THE COUNCIL OF INSURANCE AGENTS & BROKERS POLITICAL ACTION COMMITTEE",
            "type": "PAC",
            "amount": 5000
          },
          {
            "name": "TRIED-AND-TRUE PAC",
            "type": "PAC",
            "amount": 5000
          },
          {
            "name": "HMP",
            "type": "PAC",
            "amount": 5000
          },
          {
            "name": "DEFEND THE VOTE",
            "type": "PAC",
            "amount": 5000
          },
          {
            "name": "EXCHANGE CONTRACTORS FEDERAL PAC",
            "type": "PAC",
            "amount": 5000
          },
          {
            "name": "AMERICAN PHYSICAL THERAPY ASSOCIATION PHYSICAL THERAPY POLITICAL ACTION COMMITTEE (PT-PAC)",
            "type": "PAC",
            "amount": 5000
          }
        ]
      }
    ],
    "campaign": {
      "total_raised": 3498156,
      "individual_contributions": 1760432,
      "individual_itemized": 1760432,
      "individual_unitemized": 0,
      "pac_contributions": 1737724,
      "other_receipts": 0,
      "top_employers": [
        {
          "name": "GOOGLE",
          "type": "Organization",
          "amount": 34120
        },
        {
          "name": "BESSEMER VENTURE PARTNERS",
          "type": "Organization",
          "amount": 29800
        },
        {
          "name": "STANFORD UNIVERSITY",
          "type": "Organization",
          "amount": 25550
        },
        {
          "name": "BOSTON CONSULTING GROUP",
          "type": "Organization",
          "amount": 19800
        },
        {
          "name": "COOLEY LLP",
          "type": "Organization",
          "amount": 16200
        },
        {
          "name": "OVO FUND",
          "type": "Organization",
          "amount": 14900
        },
        {
          "name": "LINDSAY GOLDBERG",
          "type": "Organization",
          "amount": 13200
        },
        {
          "name": "KEKER VAN NEST & PETERS LLP",
          "type": "Organization",
          "amount": 12900
        },
        {
          "name": "N Y F PROPERTIES INC.",
          "type": "Organization",
          "amount": 12400
        },
        {
          "name": "UC BERKELEY",
          "type": "Organization",
          "amount": 10909
        },
        {
          "name": "KEKER VAN NEST & PETERS",
          "type": "Organization",
          "amount": 10400
        },
        {
          "name": "UNIVERSITY OF CALIFORNIA BERKELEY",
          "type": "Organization",
          "amount": 10100
        },
        {
          "name": "PSAI REALTY PARTNERS",
          "type": "Organization",
          "amount": 9900
        },
        {
          "name": "MANAGING PARTNER",
          "type": "Organization",
          "amount": 9900
        },
        {
          "name": "BOOZ ALLEN HAMILTON",
          "type": "Organization",
          "amount": 9900
        },
        {
          "name": "COLLINEAR NETWORKS",
          "type": "Organization",
          "amount": 8800
        },
        {
          "name": "MYSELF - BB EVENTS",
          "type": "Organization",
          "amount": 8700
        },
        {
          "name": "CANTILLON CAPITAL",
          "type": "Organization",
          "amount": 8300
        },
        {
          "name": "AC WELLNESS",
          "type": "Organization",
          "amount": 8100
        },
        {
          "name": "CTS INC.",
          "type": "Organization",
          "amount": 8000
        },
        {
          "name": "APPLE INC.",
          "type": "Organization",
          "amount": 7825
        },
        {
          "name": "Y COMBINATOR",
          "type": "Organization",
          "amount": 7600
        },
        {
          "name": "APOLLO MANAGEMENT",
          "type": "Organization",
          "amount": 7600
        },
        {
          "name": "UC DAVIS",
          "type": "Organization",
          "amount": 7350
        },
        {
          "name": "THOMSON REUTERS",
          "type": "Organization",
          "amount": 7100
        },
        {
          "name": "LINKEDIN",
          "type": "Organization",
          "amount": 7100
        },
        {
          "name": "MORGAN STANLEY",
          "type": "Organization",
          "amount": 6866
        },
        {
          "name": "E + J GALLO WINERY",
          "type": "Organization",
          "amount": 6800
        },
        {
          "name": "RICHARD BEARD ARCHITECTS",
          "type": "Organization",
          "amount": 6800
        },
        {
          "name": "REED INTERNATIONAL",
          "type": "Organization",
          "amount": 6700
        },
        {
          "name": "DATAVANT",
          "type": "Organization",
          "amount": 6700
        },
        {
          "name": "BERGGRUEN GALLERY",
          "type": "Organization",
          "amount": 6700
        },
        {
          "name": "SMUDGE WELLNESS INC.",
          "type": "Organization",
          "amount": 6700
        },
        {
          "name": "NORTHWESTERN UNIVERSITY",
          "type": "Organization",
          "amount": 6600
        },
        {
          "name": "SPECTRUM EQUITY",
          "type": "Organization",
          "amount": 6600
        },
        {
          "name": "VABA",
          "type": "Organization",
          "amount": 6600
        },
        {
          "name": "HARVARD UNIVERSITY",
          "type": "Organization",
          "amount": 6600
        },
        {
          "name": "ABVIO INC.",
          "type": "Organization",
          "amount": 6600
        },
        {
          "name": "UNITED STAFFING ASSOCIATES",
          "type": "Organization",
          "amount": 6600
        },
        {
          "name": "HILLSPIRE LLC",
          "type": "Organization",
          "amount": 6600
        },
        {
          "name": "THE SCOTT FOUNDATION",
          "type": "Organization",
          "amount": 6600
        },
        {
          "name": "VENBIO PARTNERS LLC",
          "type": "Organization",
          "amount": 6600
        },
        {
          "name": "VALLEY STRONG CREDIT UNION",
          "type": "Organization",
          "amount": 6600
        },
        {
          "name": "EVERGREEN MONEY",
          "type": "Organization",
          "amount": 6600
        },
        {
          "name": "MORRISON & FOERSTER LLC",
          "type": "Organization",
          "amount": 6600
        },
        {
          "name": "META PLATFORMS",
          "type": "Organization",
          "amount": 6600
        },
        {
          "name": "EXECUTIVE AFFILIATES",
          "type": "Organization",
          "amount": 6600
        },
        {
          "name": "ADOBE INC",
          "type": "Organization",
          "amount": 6600
        },
        {
          "name": "LA CLINICA",
          "type": "Organization",
          "amount": 6600
        },
        {
          "name": "SHER EDLING LLP",
          "type": "Organization",
          "amount": 6600
        }
      ],
      "top_pac_donors": [
        {
          "name": "NRCC",
          "type": "PAC",
          "amount": 928232
        },
        {
          "name": "NATIONAL ASSOCIATION OF REALTORS POLITICAL ACTION COMMITTEE",
          "type": "PAC",
          "amount": 91397
        },
        {
          "name": "NATIONAL ASSOCIATION OF REALTORS",
          "type": "PAC",
          "amount": 73179
        },
        {
          "name": "MAJORITY PAC",
          "type": "PAC",
          "amount": 31100
        },
        {
          "name": "FRONTLINE USA",
          "type": "PAC",
          "amount": 11600
        },
        {
          "name": "JSTREETPAC",
          "type": "PAC",
          "amount": 10446
        },
        {
          "name": "INTERNATIONAL ASSOCIATION OF SHEET METAL, AIR, RAIL AND TRANSPORTATION WORKERS POLITICAL ACTION LEAGUE",
          "type": "PAC",
          "amount": 10000
        },
        {
          "name": "END CITIZENS UNITED",
          "type": "PAC",
          "amount": 10000
        },
        {
          "name": "INTERNATIONAL BROTHERHOOD OF ELECTRICAL WORKERS POLITICAL ACTION COMMITTEE",
          "type": "PAC",
          "amount": 10000
        },
        {
          "name": "AMERICAN FEDERATION OF STATE COUNTY & MUNICIPAL EMPLOYEES  P E O P L E",
          "type": "PAC",
          "amount": 10000
        },
        {
          "name": "NATIONAL AIR TRAFFIC CONTROLLERS ASSOCIATION PAC",
          "type": "PAC",
          "amount": 10000
        },
        {
          "name": "AMERICAN CRYSTAL SUGAR COMPANY POLITICAL ACTION COMMITTEE",
          "type": "PAC",
          "amount": 10000
        },
        {
          "name": "TRUTH TO POWER",
          "type": "PAC",
          "amount": 10000
        },
        {
          "name": "MACHINISTS NON PARTISAN POLITICAL LEAGUE OF THE INTERNATIONAL ASSOCIATION OF MACHINISTS & AEROSPACE WORKERS",
          "type": "PAC",
          "amount": 10000
        },
        {
          "name": "NEW DEMOCRAT COALITION ACTION FUND",
          "type": "PAC",
          "amount": 10000
        },
        {
          "name": "JOBS, EDUCATION, & FAMILIES FIRST  JEFF PAC",
          "type": "PAC",
          "amount": 10000
        },
        {
          "name": "AMERICAN FEDERATION OF TEACHERS, AFL-CIO COMMITTEE ON POLITICAL EDUCATION",
          "type": "PAC",
          "amount": 10000
        },
        {
          "name": "AMERIPAC: THE FUND FOR A GREATER AMERICA",
          "type": "PAC",
          "amount": 10000
        },
        {
          "name": "CARPENTERS LEGISLATIVE IMPROVEMENT COMMITTEE UNITED BROTHERHOOD OF CARPENTERS AND JOINERS",
          "type": "PAC",
          "amount": 10000
        },
        {
          "name": "SEIU COPE (SERVICE EMPLOYEES INTERNATIONAL UNION COMMITTEE ON POLITICAL EDUCATION)",
          "type": "PAC",
          "amount": 10000
        },
        {
          "name": "AIR LINE PILOTS ASSOCIATION PAC",
          "type": "PAC",
          "amount": 10000
        },
        {
          "name": "DAIRY FARMERS OF AMERICA, INC. POLITICAL ACTION COMMITTEE; AKA DFA-PAC",
          "type": "PAC",
          "amount": 8000
        },
        {
          "name": "INTERNATIONAL ASSOCIATION OF FIREFIGHTERS INTERESTED IN REGISTRATION AND EDUCATION PAC",
          "type": "PAC",
          "amount": 7500
        },
        {
          "name": "ACROSS THE AISLE PAC",
          "type": "PAC",
          "amount": 7500
        },
        {
          "name": "WINE AND SPIRITS WHOLESALERS OF AMERICA, INC. POLITICAL ACTION COMMITTEE",
          "type": "PAC",
          "amount": 7500
        },
        {
          "name": "D.R.I.V.E. - DEMOCRAT, REPUBLICAN, INDEPENDENT VOTER EDUCATION (THE PAC OF THE INTERNATIONAL BROTHERHOOD OF TEAMSTERS)",
          "type": "PAC",
          "amount": 7500
        },
        {
          "name": "AMERICAN ASSOCIATION FOR JUSTICE POLITICAL ACTION COMMITTEE (AAJ PAC)",
          "type": "PAC",
          "amount": 7500
        },
        {
          "name": "BLUE DIAMOND GROWERS POLITICAL ACTION COMMITTEE",
          "type": "PAC",
          "amount": 7500
        },
        {
          "name": "FAIR SHOT PAC",
          "type": "PAC",
          "amount": 7500
        },
        {
          "name": "WINE INSTITUTE PAC",
          "type": "PAC",
          "amount": 7500
        },
        {
          "name": "NATIONAL ASSOCIATION OF LETTER CARRIERS OF U.S.A. POLITICAL FUND (LETTER CARRIER POLITICAL FUND)",
          "type": "PAC",
          "amount": 7500
        },
        {
          "name": "NEA FUND FOR CHILDREN AND PUBLIC EDUCATION",
          "type": "PAC",
          "amount": 7000
        },
        {
          "name": "PUTTING NEW HAMPSHIRE FIRST",
          "type": "PAC",
          "amount": 6600
        },
        {
          "name": "CA LUV PAC (CALIFORNIA LEADERSHIP UNITED FOR VICTORY PAC)",
          "type": "PAC",
          "amount": 6500
        },
        {
          "name": "AMERICAN ISRAEL PUBLIC AFFAIRS COMMITTEE POLITICAL ACTION COMMITTEE",
          "type": "PAC",
          "amount": 6001
        },
        {
          "name": "ENGINEERS POLITICAL EDUCATION COMMITTEE (EPEC)/INTERNATIONAL UNION OF OPERATING ENGINEERS",
          "type": "PAC",
          "amount": 6000
        },
        {
          "name": "FOLEY & LARDNER POLITICAL FUND, INC.",
          "type": "PAC",
          "amount": 6000
        },
        {
          "name": "AMERICAN MEDICAL ASSOCIATION POLITICAL ACTION COMMITTEE",
          "type": "PAC",
          "amount": 6000
        },
        {
          "name": "UA UNION PLUMBERS & PIPEFITTERS VOTE! PAC (UNITED ASSOCIATION OF JOURNEYMEN AND APPRENTICES OF THE PLUMBING & PIPEFITTING INDUSTRY OF THE UNITED STATES AND CANADA)",
          "type": "PAC",
          "amount": 5000
        },
        {
          "name": "AMERICAN VETERINARY MEDICAL ASSOCIATION POLITICAL ACTION COMMITTEE",
          "type": "PAC",
          "amount": 5000
        },
        {
          "name": "PAC TO THE FUTURE",
          "type": "PAC",
          "amount": 5000
        },
        {
          "name": "PLANNED PARENTHOOD ACTION FUND INC PAC, DBA PLANNED PARENTHOOD FEDERAL PAC",
          "type": "PAC",
          "amount": 5000
        },
        {
          "name": "DEFEND THE DREAM",
          "type": "PAC",
          "amount": 5000
        },
        {
          "name": "ASIAN AMERICAN HOTEL OWNERS ASSOCIATION PAC (AAHOA PAC)",
          "type": "PAC",
          "amount": 5000
        },
        {
          "name": "THE COUNCIL OF INSURANCE AGENTS & BROKERS POLITICAL ACTION COMMITTEE",
          "type": "PAC",
          "amount": 5000
        },
        {
          "name": "TRIED-AND-TRUE PAC",
          "type": "PAC",
          "amount": 5000
        },
        {
          "name": "HMP",
          "type": "PAC",
          "amount": 5000
        },
        {
          "name": "DEFEND THE VOTE",
          "type": "PAC",
          "amount": 5000
        },
        {
          "name": "EXCHANGE CONTRACTORS FEDERAL PAC",
          "type": "PAC",
          "amount": 5000
        },
        {
          "name": "AMERICAN PHYSICAL THERAPY ASSOCIATION PHYSICAL THERAPY POLITICAL ACTION COMMITTEE (PT-PAC)",
          "type": "PAC",
          "amount": 5000
        }
      ]
    },
    "leadership_pacs": []
  },
  "donor_alignment": {
    "overall_pct": 61,
    "total_votes_scored": 66,
    "methodology_url": "/methodology#donor-alignment",
    "examples": [
      {
        "vote_description": "Middle Class Borrower Protection Act",
        "bill": "HR3564",
        "date": "2023-06-23",
        "member_voted": "Yea",
        "aligned": true,
        "donor_category": "Real estate industry",
        "donor_expected": "Yea",
        "confidence": 0.8,
        "reason": "Middle Class Borrower Protection Act \u2014 eliminates FHFA fee structure that charged higher-credit borrowers more to cross-subsidize lower-credit borrowers. Realtors and mortgage lenders supported this as it reduces costs for their core buyer demographic."
      },
      {
        "vote_description": "Protecting Prudent Investment of Retirement Savings Act",
        "bill": "HR2988",
        "date": "2026-01-15",
        "member_voted": "Nay",
        "aligned": true,
        "donor_category": "Labor unions",
        "donor_expected": "Nay",
        "confidence": 0.9,
        "reason": "Protecting Prudent Investment of Retirement Savings Act \u2014 despite the name, this ROLLS BACK the DOL ESG investing rule, restricting how pension funds (including union pension funds) can consider environmental and social factors when investing. Unions strongly opposed this bill."
      },
      {
        "vote_description": "Whole Milk for Healthy Kids Act",
        "bill": "HR1147",
        "date": "2023-12-13",
        "member_voted": "Yea",
        "aligned": true,
        "donor_category": "Agriculture industry",
        "donor_expected": "Yea",
        "confidence": 0.8,
        "reason": "Whole Milk for Healthy Kids Act \u2014 allows schools to offer whole-fat milk and flavored milk, supported by the dairy industry and National Dairy Council as it increases school milk sales."
      },
      {
        "vote_description": "Full-Year Continuing Appropriations and Extensions Act, 2025",
        "bill": "HR1968",
        "date": "2025-03-11",
        "member_voted": "Nay",
        "aligned": false,
        "donor_category": "Labor unions",
        "donor_expected": "Yea",
        "confidence": 0.8,
        "reason": "Amendment to reinstate veteran federal employees fired without cause \u2014 federal employee unions strongly support protections against arbitrary dismissal of federal workers."
      },
      {
        "vote_description": "Agriculture, Rural Development, Food and Drug Administration, and Related Agencies Appropriations Act, 2024",
        "bill": "HR4368",
        "date": "2023-09-28",
        "member_voted": "Nay",
        "aligned": false,
        "donor_category": "Agriculture industry",
        "donor_expected": "Yea",
        "confidence": 0.85,
        "reason": "FY2024 Agriculture Appropriations Act \u2014 funds USDA programs, crop insurance, farm subsidies, and food safety that the farm bureau and agricultural companies depend on."
      }
    ]
  },
  "electorate_alignment": {
    "issues_scored": 9,
    "against_electorate_pct": 11,
    "highlights": [
      {
        "issue": "Universal background checks for gun purchases",
        "district_support_pct": 89.4,
        "margin_of_error": 5.3,
        "member_position": "Voted Yea",
        "aligned_with_electorate": true,
        "aligned_with_donors": false
      },
      {
        "issue": "Ban on assault-style weapons",
        "district_support_pct": 65.6,
        "margin_of_error": 8.1,
        "member_position": "Voted Yea",
        "aligned_with_electorate": true,
        "aligned_with_donors": false
      },
      {
        "issue": "Abortion should always be legal",
        "district_support_pct": 62.8,
        "margin_of_error": 9.4,
        "member_position": "Voted Yea",
        "aligned_with_electorate": true,
        "aligned_with_donors": false
      },
      {
        "issue": "Prohibit all abortions after 20 weeks",
        "district_support_pct": 18.8,
        "margin_of_error": 6.2,
        "member_position": "Voted Nay",
        "aligned_with_electorate": true,
        "aligned_with_donors": false
      },
      {
        "issue": "Support the Affordable Care Act",
        "district_support_pct": 61.3,
        "margin_of_error": 8.2,
        "member_position": "Voted Yea",
        "aligned_with_electorate": true,
        "aligned_with_donors": false
      },
      {
        "issue": "Regulate CO2 as a pollutant",
        "district_support_pct": 72.4,
        "margin_of_error": 6.9,
        "member_position": "Voted Yea",
        "aligned_with_electorate": true,
        "aligned_with_donors": false
      },
      {
        "issue": "Require minimum renewable fuel production",
        "district_support_pct": 66.5,
        "margin_of_error": 7.4,
        "member_position": "Voted Yea",
        "aligned_with_electorate": true,
        "aligned_with_donors": false
      },
      {
        "issue": "Build a wall on the U.S.-Mexico border",
        "district_support_pct": 32.9,
        "margin_of_error": 7.7,
        "member_position": "Voted Nay",
        "aligned_with_electorate": true,
        "aligned_with_donors": false
      },
      {
        "issue": "Require permits to carry concealed guns",
        "district_support_pct": 64.8,
        "margin_of_error": 7.5,
        "member_position": "Voted Yea",
        "aligned_with_electorate": false,
        "aligned_with_donors": false
      }
    ],
    "against_electorate_with_donors": [],
    "source": "mrp-ces"
  },
  "links": {
    "voting_record": "https://www.congress.gov/member/josh-harder/H001090",
    "opensecrets": "https://www.opensecrets.org/members-of-congress/summary?cid=N00040853",
    "official_website": "https://harder.house.gov"
  }
}